[
    {
        "id": 498874,
        "active": true,
        "customer_id": 1351322,
        "addresspackstation_id": null,
        "addresspostoffice_id": null,
        "addressstreet_id": 489763,
        "gender": 0,
        "firstname": "Karin",
        "lastname": "Berger-L\u00fc\u00dfmann",
        "postcode": 92242,
        "city": "Hirschau",
        "street": "Friedrich-Zeitler-Str.",
        "housenumber": 30,
        "address": "Friedrich-Zeitler-Str. 30",
        "country_code": "DE",
        "country_name": "Deutschland",
        "company": null
    },
    {
        "id": 498873,
        "active": true,
        "customer_id": 1351321,
        "addresspackstation_id": null,
        "addresspostoffice_id": null,
        "addressstreet_id": 489762,
        "gender": 0,
        "firstname": "Johanna",
        "lastname": "Jaeger",
        "postcode": 80805,
        "city": "M\u00fcnchen",
        "street": "Johann-Fichte-Str",
        "housenumber": 11,
        "address": "Johann-Fichte-Str 11",
        "country_code": "DE",
        "country_name": "Deutschland",
        "company": null
    },
    {
        "id": 498872,
        "active": true,
        "customer_id": 1351320,
        "addresspackstation_id": null,
        "addresspostoffice_id": null,
        "addressstreet_id": 489761,
        "gender": 0,
        "firstname": "silke",
        "lastname": "malledent",
        "postcode": 544454472,
        "city": "brauneberg",
        "street": "unter der h\u00f6ht",
        "housenumber": 2,
        "address": "unter der h\u00f6ht 2",
        "country_code": "DE",
        "country_name": "Deutschland",
        "company": null
    },
    {
        "id": 498867,
        "active": true,
        "customer_id": 1351319,
        "addresspackstation_id": null,
        "addresspostoffice_id": null,
        "addressstreet_id": 489757,
        "gender": 0,
        "firstname": "Marlene",
        "lastname": "G\u00e4hle",
        "postcode": 31535,
        "city": "Neustadt",
        "street": "Resser Weg",
        "housenumber": 5,
        "address": "Resser Weg 5",
        "country_code": "DE",
        "country_name": "Deutschland",
        "company": null
    },
    {
        "id": 498866,
        "active": true,
        "customer_id": 1351318,
        "addresspackstation_id": null,
        "addresspostoffice_id": null,
        "addressstreet_id": 489756,
        "gender": 0,
        "firstname": "Nadine",
        "lastname": "Groener",
        "postcode": 88131,
        "city": "Lindau",
        "street": "Steigstrasse 21",
        "housenumber": "Steigstrasse 21",
        "address": "Steigstrasse 21 Steigstrasse 21",
        "country_code": "DE",
        "country_name": "Deutschland",
        "company": "Frau"
    },
    {
        "id": 498865,
        "active": true,
        "customer_id": 1351317,
        "addresspackstation_id": null,
        "addresspostoffice_id": null,
        "addressstreet_id": 489755,
        "gender": 0,
        "firstname": "Annelie",
        "lastname": "M\u00fcller",
        "postcode": 52076,
        "city": "Aachen",
        "street": "Hochhausring",
        "housenumber": 10,
        "address": "Hochhausring 10",
        "country_code": "DE",
        "country_name": "Deutschland",
        "company": null
    },
    {
        "id": 498864,
        "active": true,
        "customer_id": 1351316,
        "addresspackstation_id": null,
        "addresspostoffice_id": null,
        "addressstreet_id": 489754,
        "gender": 0,
        "firstname": "Theresa",
        "lastname": "Meier",
        "postcode": 60329,
        "city": "Frankfurt",
        "street": "Kaiserstr.",
        "housenumber": "58c",
        "address": "Kaiserstr. 58c",
        "country_code": "DE",
        "country_name": "Deutschland",
        "company": null
    },
    {
        "id": 498862,
        "active": true,
        "customer_id": 1351315,
        "addresspackstation_id": null,
        "addresspostoffice_id": null,
        "addressstreet_id": 489752,
        "gender": 0,
        "firstname": "Corinna",
        "lastname": "Ladwig",
        "postcode": 26919,
        "city": "Brake",
        "street": "Hafenstrasse",
        "housenumber": 2,
        "address": "Hafenstrasse 2",
        "country_code": "DE",
        "country_name": "Deutschland",
        "company": "Zeit \u0026 Service"
    },
    {
        "id": 498863,
        "active": true,
        "customer_id": 1351315,
        "addresspackstation_id": null,
        "addresspostoffice_id": null,
        "addressstreet_id": 489753,
        "gender": 0,
        "firstname": "Corinna",
        "lastname": "Ladwig",
        "postcode": 26969,
        "city": "Butjadingen",
        "street": "Syuggewarder Weg 10",
        "housenumber": "Syuggewarder Weg 10",
        "address": "Syuggewarder Weg 10 Syuggewarder Weg 10",
        "country_code": "DE",
        "country_name": "Deutschland",
        "company": null
    },
    {
        "id": 498861,
        "active": true,
        "customer_id": 1351314,
        "addresspackstation_id": null,
        "addresspostoffice_id": null,
        "addressstreet_id": 489751,
        "gender": 0,
        "firstname": "Miriam",
        "lastname": "Gm\u00f6hling",
        "postcode": 70197,
        "city": "Stuttgart",
        "street": "R\u00f6testra\u00dfe",
        "housenumber": 51,
        "address": "R\u00f6testra\u00dfe 51",
        "country_code": "DE",
        "country_name": "Deutschland",
        "company": null
    },
    {
        "id": 498860,
        "active": true,
        "customer_id": 1351313,
        "addresspackstation_id": null,
        "addresspostoffice_id": null,
        "addressstreet_id": 489750,
        "gender": 0,
        "firstname": "Marion",
        "lastname": "Proba",
        "postcode": 63543,
        "city": "Neuberg",
        "street": "Hainstrasse",
        "housenumber": 13,
        "address": "Hainstrasse 13",
        "country_code": "DE",
        "country_name": "Deutschland",
        "company": null
    },
    {
        "id": 498859,
        "active": true,
        "customer_id": 1351312,
        "addresspackstation_id": null,
        "addresspostoffice_id": null,
        "addressstreet_id": 489749,
        "gender": 0,
        "firstname": "Lisanne",
        "lastname": "Kolling",
        "postcode": 86199,
        "city": "Augsburg",
        "street": "Ludwig-Ottler-Str.",
        "housenumber": 11,
        "address": "Ludwig-Ottler-Str. 11",
        "country_code": "DE",
        "country_name": "Deutschland",
        "company": null
    },
    {
        "id": 498858,
        "active": true,
        "customer_id": 1351311,
        "addresspackstation_id": null,
        "addresspostoffice_id": null,
        "addressstreet_id": 489748,
        "gender": 1,
        "firstname": "Johanna",
        "lastname": "Hirsch",
        "postcode": 69226,
        "city": "Nu\u00dfloch",
        "street": "Jahnstra\u00dfe",
        "housenumber": 20,
        "address": "Jahnstra\u00dfe 20",
        "country_code": "DE",
        "country_name": "Deutschland",
        "company": null
    },
    {
        "id": 498853,
        "active": true,
        "customer_id": 1351310,
        "addresspackstation_id": null,
        "addresspostoffice_id": null,
        "addressstreet_id": 489743,
        "gender": 0,
        "firstname": "Silke",
        "lastname": "Zumpe",
        "postcode": "01458",
        "city": "Ottendorf-Okrilla",
        "street": "Dresdner Str.",
        "housenumber": 40,
        "address": "Dresdner Str. 40",
        "country_code": "DE",
        "country_name": "Deutschland",
        "company": null
    },
    {
        "id": 498849,
        "active": true,
        "customer_id": 1351309,
        "addresspackstation_id": null,
        "addresspostoffice_id": null,
        "addressstreet_id": 489739,
        "gender": 0,
        "firstname": "Anna",
        "lastname": "Eichhorn",
        "postcode": 98666,
        "city": "Einsiedel",
        "street": "Bibergrundstra\u00dfe",
        "housenumber": 29,
        "address": "Bibergrundstra\u00dfe 29",
        "country_code": "DE",
        "country_name": "Deutschland",
        "company": null
    },
    {
        "id": 498848,
        "active": true,
        "customer_id": 1351308,
        "addresspackstation_id": null,
        "addresspostoffice_id": null,
        "addressstreet_id": 489738,
        "gender": 0,
        "firstname": "Elisabeth",
        "lastname": "Lutzky",
        "postcode": 2130,
        "city": "Mistelbach",
        "street": "Mitschastra\u00dfe",
        "housenumber": 34,
        "address": "Mitschastra\u00dfe 34",
        "country_code": "AT",
        "country_name": "\u00d6sterreich",
        "company": null
    },
    {
        "id": 498847,
        "active": true,
        "customer_id": 1351307,
        "addresspackstation_id": null,
        "addresspostoffice_id": null,
        "addressstreet_id": 489737,
        "gender": 0,
        "firstname": "Goldschmidt",
        "lastname": "Juliana",
        "postcode": 86399,
        "city": "Bobingen",
        "street": "Jahnstrasse",
        "housenumber": "5a",
        "address": "Jahnstrasse 5a",
        "country_code": "DE",
        "country_name": "Deutschland",
        "company": "Frau"
    },
    {
        "id": 498845,
        "active": true,
        "customer_id": 1351306,
        "addresspackstation_id": null,
        "addresspostoffice_id": null,
        "addressstreet_id": 489735,
        "gender": 0,
        "firstname": "Sabrina",
        "lastname": "Mark",
        "postcode": 81677,
        "city": "Munich",
        "street": "Wilhelm-Tell-Strasse 3",
        "housenumber": "Wilhelm-Tell-Strasse 3",
        "address": "Wilhelm-Tell-Strasse 3 Wilhelm-Tell-Strasse 3",
        "country_code": "DE",
        "country_name": "Deutschland",
        "company": null
    },
    {
        "id": 498844,
        "active": true,
        "customer_id": 1351305,
        "addresspackstation_id": null,
        "addresspostoffice_id": null,
        "addressstreet_id": 489734,
        "gender": 0,
        "firstname": "Christine",
        "lastname": "Ploch",
        "postcode": 60325,
        "city": "Frankfurt",
        "street": "Beethovenstra\u00dfe",
        "housenumber": 56,
        "address": "Beethovenstra\u00dfe 56",
        "country_code": "DE",
        "country_name": "Deutschland",
        "company": null
    },
    {
        "id": 498841,
        "active": true,
        "customer_id": 1351304,
        "addresspackstation_id": null,
        "addresspostoffice_id": null,
        "addressstreet_id": 489731,
        "gender": 0,
        "firstname": "Franziska",
        "lastname": "Legler",
        "postcode": 52064,
        "city": "Aachen",
        "street": "Boxgraben",
        "housenumber": 138,
        "address": "Boxgraben 138",
        "country_code": "DE",
        "country_name": "Deutschland",
        "company": null
    },
    {
        "id": 498843,
        "active": true,
        "customer_id": 1351304,
        "addresspackstation_id": null,
        "addresspostoffice_id": null,
        "addressstreet_id": 489733,
        "gender": 0,
        "firstname": "Franziska",
        "lastname": "Simon",
        "postcode": 52064,
        "city": "Aachen",
        "street": "Boxgraben",
        "housenumber": 138,
        "address": "Boxgraben 138",
        "country_code": "DE",
        "country_name": "Deutschland",
        "company": null
    },
    {
        "id": 498840,
        "active": true,
        "customer_id": 1351304,
        "addresspackstation_id": null,
        "addresspostoffice_id": null,
        "addressstreet_id": 489730,
        "gender": 0,
        "firstname": "Franziska",
        "lastname": "Legler",
        "postcode": 13359,
        "city": "Berlin",
        "street": "Gr\u00fcntaler Stra\u00dfe",
        "housenumber": 48,
        "address": "Gr\u00fcntaler Stra\u00dfe 48",
        "country_code": "DE",
        "country_name": "Deutschland",
        "company": "c\/o Franziska Simon"
    },
    {
        "id": 498842,
        "active": true,
        "customer_id": 1351304,
        "addresspackstation_id": null,
        "addresspostoffice_id": null,
        "addressstreet_id": 489732,
        "gender": 0,
        "firstname": "Franziska",
        "lastname": "Legler",
        "postcode": 13359,
        "city": "Berlin",
        "street": "Gr\u00fcntaler Stra\u00dfe",
        "housenumber": 48,
        "address": "Gr\u00fcntaler Stra\u00dfe 48",
        "country_code": "DE",
        "country_name": "Deutschland",
        "company": "c\/o Franziska Simon"
    },
    {
        "id": 498838,
        "active": true,
        "customer_id": 1351303,
        "addresspackstation_id": 8701,
        "addresspostoffice_id": null,
        "addressstreet_id": null,
        "gender": 0,
        "firstname": "Linda",
        "lastname": "P\u00e9us",
        "postcode": 77652,
        "city": "Offenburg",
        "street": null,
        "housenumber": null,
        "address": "842418085 Packstation 102",
        "country_code": "DE",
        "country_name": "Deutschland",
        "company": null
    },
    {
        "id": 498839,
        "active": true,
        "customer_id": 1351303,
        "addresspackstation_id": null,
        "addresspostoffice_id": null,
        "addressstreet_id": 489729,
        "gender": 0,
        "firstname": "Linda",
        "lastname": "P\u00e9us",
        "postcode": 77654,
        "city": "Offenburg",
        "street": "Goethestr",
        "housenumber": 9,
        "address": "Goethestr 9",
        "country_code": "DE",
        "country_name": "Deutschland",
        "company": null
    },
    {
        "id": 498837,
        "active": true,
        "customer_id": 1351302,
        "addresspackstation_id": null,
        "addresspostoffice_id": null,
        "addressstreet_id": 489728,
        "gender": 0,
        "firstname": "Carmen",
        "lastname": "Zettl",
        "postcode": 84034,
        "city": "Landshut",
        "street": "Kl\u00f6tzlm\u00fcllerstr",
        "housenumber": 70,
        "address": "Kl\u00f6tzlm\u00fcllerstr 70",
        "country_code": "DE",
        "country_name": "Deutschland",
        "company": null
    },
    {
        "id": 498833,
        "active": true,
        "customer_id": 1351301,
        "addresspackstation_id": null,
        "addresspostoffice_id": null,
        "addressstreet_id": 489725,
        "gender": 0,
        "firstname": "Anna lena",
        "lastname": "Gerdelmann",
        "postcode": 49740,
        "city": "Hasel\u00fcnne",
        "street": "Kreyenborg",
        "housenumber": 13,
        "address": "Kreyenborg 13",
        "country_code": "DE",
        "country_name": "Deutschland",
        "company": null
    },
    {
        "id": 498831,
        "active": true,
        "customer_id": 1351300,
        "addresspackstation_id": null,
        "addresspostoffice_id": null,
        "addressstreet_id": 489723,
        "gender": 0,
        "firstname": "Katharina",
        "lastname": "Gode",
        "postcode": 10961,
        "city": "Berlin",
        "street": "Schleiermacherstra\u00dfe",
        "housenumber": 12,
        "address": "Schleiermacherstra\u00dfe 12",
        "country_code": "DE",
        "country_name": "Deutschland",
        "company": null
    },
    {
        "id": 498830,
        "active": true,
        "customer_id": 1351300,
        "addresspackstation_id": 8699,
        "addresspostoffice_id": null,
        "addressstreet_id": null,
        "gender": 0,
        "firstname": "Katharina",
        "lastname": "Gode",
        "postcode": 10961,
        "city": "Berlin",
        "street": null,
        "housenumber": null,
        "address": "841420790 Packstation 189",
        "country_code": "DE",
        "country_name": "Deutschland",
        "company": null
    },
    {
        "id": 498829,
        "active": true,
        "customer_id": 1351299,
        "addresspackstation_id": null,
        "addresspostoffice_id": null,
        "addressstreet_id": 489722,
        "gender": 0,
        "firstname": "Tatjana",
        "lastname": "Zenoni",
        "postcode": 8142,
        "city": "Uitikon",
        "street": "Pfaffenacherstr.",
        "housenumber": 5,
        "address": "Pfaffenacherstr. 5",
        "country_code": "DE",
        "country_name": "Deutschland",
        "company": null
    },
    {
        "id": 498828,
        "active": true,
        "customer_id": 1351299,
        "addresspackstation_id": null,
        "addresspostoffice_id": null,
        "addressstreet_id": 489721,
        "gender": 0,
        "firstname": "Mandy",
        "lastname": "Klein",
        "postcode": 78462,
        "city": "Konstanz",
        "street": "Bahnhofstr.",
        "housenumber": 6,
        "address": "Bahnhofstr. 6",
        "country_code": "DE",
        "country_name": "Deutschland",
        "company": null
    },
    {
        "id": 498826,
        "active": true,
        "customer_id": 1351298,
        "addresspackstation_id": null,
        "addresspostoffice_id": null,
        "addressstreet_id": 489719,
        "gender": 0,
        "firstname": "Gwendolin",
        "lastname": "Koch",
        "postcode": 80802,
        "city": "M\u00fcnchen",
        "street": "M\u00fcnchner Freiheit",
        "housenumber": 24,
        "address": "M\u00fcnchner Freiheit 24",
        "country_code": "DE",
        "country_name": "Deutschland",
        "company": null
    },
    {
        "id": 498824,
        "active": true,
        "customer_id": 1351297,
        "addresspackstation_id": null,
        "addresspostoffice_id": null,
        "addressstreet_id": 489717,
        "gender": 0,
        "firstname": "Nicola",
        "lastname": "Rosbach",
        "postcode": 65594,
        "city": "Runkel",
        "street": "Beethovenstr.",
        "housenumber": 6,
        "address": "Beethovenstr. 6",
        "country_code": "DE",
        "country_name": "Deutschland",
        "company": null
    },
    {
        "id": 498823,
        "active": true,
        "customer_id": 1351296,
        "addresspackstation_id": null,
        "addresspostoffice_id": null,
        "addressstreet_id": 489716,
        "gender": 0,
        "firstname": "Carolin",
        "lastname": "Speckner",
        "postcode": 91275,
        "city": "Auerbach",
        "street": "Hauptstr. 9",
        "housenumber": 9,
        "address": "Hauptstr. 9 9",
        "country_code": "DE",
        "country_name": "Deutschland",
        "company": null
    },
    {
        "id": 498822,
        "active": true,
        "customer_id": 1351295,
        "addresspackstation_id": null,
        "addresspostoffice_id": null,
        "addressstreet_id": 489715,
        "gender": 0,
        "firstname": "Semiha",
        "lastname": "Fischer",
        "postcode": 60435,
        "city": "Frankfurt",
        "street": "Alkmenestra\u00dfe",
        "housenumber": 49,
        "address": "Alkmenestra\u00dfe 49",
        "country_code": "DE",
        "country_name": "Deutschland",
        "company": null
    },
    {
        "id": 498821,
        "active": true,
        "customer_id": 1351294,
        "addresspackstation_id": null,
        "addresspostoffice_id": null,
        "addressstreet_id": 489714,
        "gender": 0,
        "firstname": "Nicole",
        "lastname": "Deitert",
        "postcode": 50769,
        "city": "K\u00f6ln",
        "street": "Sinnersdorfer Str.",
        "housenumber": 116,
        "address": "Sinnersdorfer Str. 116",
        "country_code": "DE",
        "country_name": "Deutschland",
        "company": null
    },
    {
        "id": 498820,
        "active": true,
        "customer_id": 1351293,
        "addresspackstation_id": null,
        "addresspostoffice_id": null,
        "addressstreet_id": 489713,
        "gender": 0,
        "firstname": "Susanne",
        "lastname": "Kohl",
        "postcode": 25767,
        "city": "Albersdorf",
        "street": "Neuer Weg",
        "housenumber": 10,
        "address": "Neuer Weg 10",
        "country_code": "DE",
        "country_name": "Deutschland",
        "company": null
    },
    {
        "id": 498818,
        "active": true,
        "customer_id": 1351292,
        "addresspackstation_id": null,
        "addresspostoffice_id": null,
        "addressstreet_id": 489711,
        "gender": 0,
        "firstname": "Laura",
        "lastname": "Meyer",
        "postcode": 50259,
        "city": "Pulheim",
        "street": "Aggerstra\u00dfe",
        "housenumber": 28,
        "address": "Aggerstra\u00dfe 28",
        "country_code": "DE",
        "country_name": "Deutschland",
        "company": null
    },
    {
        "id": 498815,
        "active": true,
        "customer_id": 1351291,
        "addresspackstation_id": null,
        "addresspostoffice_id": null,
        "addressstreet_id": 489708,
        "gender": 0,
        "firstname": "Magdalena",
        "lastname": "Pappas",
        "postcode": 63517,
        "city": "Rodenbach",
        "street": "Hanauer Landstra\u00dfe",
        "housenumber": "24b",
        "address": "Hanauer Landstra\u00dfe 24b",
        "country_code": "DE",
        "country_name": "Deutschland",
        "company": null
    },
    {
        "id": 498814,
        "active": true,
        "customer_id": 1351290,
        "addresspackstation_id": null,
        "addresspostoffice_id": null,
        "addressstreet_id": 489707,
        "gender": 0,
        "firstname": "Silke",
        "lastname": "Konermann",
        "postcode": 48565,
        "city": "Steinfurt",
        "street": "Grottenkamp",
        "housenumber": 75,
        "address": "Grottenkamp 75",
        "country_code": "DE",
        "country_name": "Deutschland",
        "company": null
    },
    {
        "id": 498812,
        "active": true,
        "customer_id": 1351289,
        "addresspackstation_id": null,
        "addresspostoffice_id": null,
        "addressstreet_id": 489705,
        "gender": 1,
        "firstname": "alessio",
        "lastname": "etairidis",
        "postcode": 73033,
        "city": "G\u00f6ppingen",
        "street": "Babenbergerstra\u00dfe",
        "housenumber": 2,
        "address": "Babenbergerstra\u00dfe 2",
        "country_code": "DE",
        "country_name": "Deutschland",
        "company": null
    },
    {
        "id": 498811,
        "active": true,
        "customer_id": 1351288,
        "addresspackstation_id": null,
        "addresspostoffice_id": null,
        "addressstreet_id": 489704,
        "gender": 0,
        "firstname": "Doris",
        "lastname": "Kr\u00e4utner",
        "postcode": 49205,
        "city": "Hasbergen",
        "street": "Schlesische Str.",
        "housenumber": 20,
        "address": "Schlesische Str. 20",
        "country_code": "DE",
        "country_name": "Deutschland",
        "company": null
    },
    {
        "id": 498810,
        "active": true,
        "customer_id": 1351287,
        "addresspackstation_id": null,
        "addresspostoffice_id": null,
        "addressstreet_id": 489703,
        "gender": 0,
        "firstname": "Andrea",
        "lastname": "Michailis",
        "postcode": 33803,
        "city": "Steinhagen",
        "street": "Leipziger Stra\u00dfe",
        "housenumber": 12,
        "address": "Leipziger Stra\u00dfe 12",
        "country_code": "DE",
        "country_name": "Deutschland",
        "company": null
    },
    {
        "id": 498809,
        "active": true,
        "customer_id": 1351286,
        "addresspackstation_id": null,
        "addresspostoffice_id": null,
        "addressstreet_id": 489702,
        "gender": 0,
        "firstname": "Kathrin",
        "lastname": "Reichert",
        "postcode": 60318,
        "city": "Frankfurt",
        "street": "Sternstrasse",
        "housenumber": 36,
        "address": "Sternstrasse 36",
        "country_code": "DE",
        "country_name": "Deutschland",
        "company": null
    },
    {
        "id": 498808,
        "active": true,
        "customer_id": 1351286,
        "addresspackstation_id": null,
        "addresspostoffice_id": null,
        "addressstreet_id": 489701,
        "gender": 0,
        "firstname": "Kathrin",
        "lastname": "Reichert",
        "postcode": 60311,
        "city": "Frankfurt",
        "street": "Kaiserstrasse",
        "housenumber": 13,
        "address": "Kaiserstrasse 13",
        "country_code": "DE",
        "country_name": "Deutschland",
        "company": "Survey Sampling Deutschland"
    },
    {
        "id": 498807,
        "active": true,
        "customer_id": 1351285,
        "addresspackstation_id": null,
        "addresspostoffice_id": null,
        "addressstreet_id": 489700,
        "gender": 0,
        "firstname": "kerstin",
        "lastname": "sch\u00e4fer",
        "postcode": 58239,
        "city": "schwerte",
        "street": "zum gro\u00dfen feld 85",
        "housenumber": 85,
        "address": "zum gro\u00dfen feld 85 85",
        "country_code": "DE",
        "country_name": "Deutschland",
        "company": null
    },
    {
        "id": 498806,
        "active": true,
        "customer_id": 1351284,
        "addresspackstation_id": null,
        "addresspostoffice_id": null,
        "addressstreet_id": 489699,
        "gender": 0,
        "firstname": "Irena",
        "lastname": "Petera",
        "postcode": 12105,
        "city": "Berlin",
        "street": "Riegerzeile",
        "housenumber": 16,
        "address": "Riegerzeile 16",
        "country_code": "DE",
        "country_name": "Deutschland",
        "company": null
    },
    {
        "id": 498804,
        "active": true,
        "customer_id": 1351283,
        "addresspackstation_id": null,
        "addresspostoffice_id": null,
        "addressstreet_id": 489697,
        "gender": 0,
        "firstname": "Andrea",
        "lastname": "Berini",
        "postcode": 79576,
        "city": "Weil am Rhein",
        "street": "Hauptstrasse",
        "housenumber": 396,
        "address": "Hauptstrasse 396",
        "country_code": "DE",
        "country_name": "Deutschland",
        "company": "c\/o LAS Burg 81232"
    },
    {
        "id": 498805,
        "active": true,
        "customer_id": 1351283,
        "addresspackstation_id": null,
        "addresspostoffice_id": null,
        "addressstreet_id": 489698,
        "gender": 0,
        "firstname": "Andrea",
        "lastname": "Berini",
        "postcode": "CH 4132",
        "city": "Muttenz",
        "street": "Schlossbergstrasse",
        "housenumber": 7,
        "address": "Schlossbergstrasse 7",
        "country_code": "DE",
        "country_name": "Deutschland",
        "company": null
    },
    {
        "id": 498803,
        "active": true,
        "customer_id": 1351282,
        "addresspackstation_id": null,
        "addresspostoffice_id": null,
        "addressstreet_id": 489696,
        "gender": 0,
        "firstname": "Carmen",
        "lastname": "K\u00f6rffer",
        "postcode": 52391,
        "city": "Vettweiss",
        "street": "Martinusstrasse",
        "housenumber": 61,
        "address": "Martinusstrasse 61",
        "country_code": "DE",
        "country_name": "Deutschland",
        "company": null
    }
]
